fundus_lesions_toolkit/__init__.py
fundus_lesions_toolkit/constants.py
fundus_lesions_toolkit/data/__init__.py
fundus_lesions_toolkit/data/dataset.py
fundus_lesions_toolkit/losses/__init__.py
fundus_lesions_toolkit/losses/contrastive_loss.py
fundus_lesions_toolkit/models/__init__.py
fundus_lesions_toolkit/models/checkpoints.py
fundus_lesions_toolkit/models/segmentation.py
fundus_lesions_toolkit/utils/__init__.py
fundus_lesions_toolkit/utils/images.py
fundus_lesions_toolkit/utils/visualization.py
fundus_lesions_toolkit-0.1.0b0.dist-info/METADATA
fundus_lesions_toolkit-0.1.0b0.dist-info/WHEEL
fundus_lesions_toolkit-0.1.0b0.dist-info/licenses/LICENSE
fundus_lesions_toolkit-0.1.0b0.dist-info/RECORD
