Metadata-Version: 2.1
Name: fundus_lesions_toolkit
Version: 0.1.0b0
Summary: Tools for lesions segmentation in retinal fundus images
Project-URL: Homepage, https://github.com/ClementPla/fundus-lesions-toolkit/
Project-URL: Bug Tracker, https://github.com/ClementPla/fundus-lesions-toolkit/issues
Author-email: Clement Playout <clement.playout@polymtl.ca>
License-File: LICENSE
Classifier: License :: OSI Approved :: MIT License
Classifier: Operating System :: OS Independent
Classifier: Programming Language :: Python :: 3
Requires-Python: >=3.5
Requires-Dist: matplotlib
Requires-Dist: nntools
Requires-Dist: numpy
Requires-Dist: opencv-python
Requires-Dist: torch
Requires-Dist: torchvision
